Kscraper/__init__.py
Kscraper/client.py
kscraper-1.2.0.dist-info/METADATA
kscraper-1.2.0.dist-info/WHEEL
kscraper-1.2.0.dist-info/top_level.txt
kscraper-1.2.0.dist-info/RECORD
