Metadata-Version: 2.4
Name: Kscraper
Version: 1.2.0
Summary: A Python package to bypass cloudflare on kick.com
Home-page: https://github.com/chardWTF/Kscraper
Author: chard
Author-email: chard@azr.tools
Classifier: Programming Language :: Python :: 3
Classifier: License :: OSI Approved :: MIT License
Classifier: Operating System :: OS Independent
Requires-Python: >=3.6
Requires-Dist: tls_client
Requires-Dist: requests
Requires-Dist: colorama
Dynamic: author
Dynamic: author-email
Dynamic: classifier
Dynamic: description
Dynamic: description-content-type
Dynamic: home-page
Dynamic: requires-dist
Dynamic: requires-python
Dynamic: summary
